{
  "holdings": [
    {
      "id": 1,
      "coin": "BTC",
      "coinName": "Bitcoin",
      "logo": "/mock/images/bitcoin.svg",
      "totalHolding": 0.63776,
      "averageBuyPrice": 55320.15,
      "currentPrice": 55320.15,
      "stcg": {
        "amount": -1200,
        "coins": 0.338
      },
      "ltcg": {
        "amount": 2400,
        "coins": 0.300
      }
    },
    {
      "id": 2,
      "coin": "ETH",
      "coinName": "Ethereum",
      "logo": "/mock/images/ethereum.svg",
      "totalHolding": 5.6736,
      "averageBuyPrice": 1620.15,
      "currentPrice": 1643.21,
      "stcg": {
        "amount": 55320.15,
        "coins": 2.332
      },
      "ltcg": {
        "amount": 8239.29,
        "coins": 3.245
      }
    },
    {
      "id": 3,
      "coin": "USDT",
      "coinName": "Tether",
      "logo": "/mock/images/tether.svg",
      "totalHolding": 3096.54,
      "averageBuyPrice": 1.15,
      "currentPrice": 1.01,
      "stcg": {
        "amount": -1200,
        "coins": 2011.23
      },
      "ltcg": {
        "amount": 2400,
        "coins": 802.47
      }
    },
    {
      "id": 4,
      "coin": "MATIC",
      "coinName": "Polygon",
      "logo": "/mock/images/polygon.svg",
      "totalHolding": 2210,
      "averageBuyPrice": 2.31,
      "currentPrice": 2.11,
      "stcg": {
        "amount": -1200,
        "coins": 802
      },
      "ltcg": {
        "amount": 2400,
        "coins": 1402
      }
    },
    {
      "id": 5,
      "coin": "ETH",
      "coinName": "Ethereum",
      "logo": "/mock/images/ethereum.svg",
      "totalHolding": 5.6736,
      "averageBuyPrice": 1620.15,
      "currentPrice": 1643.21,
      "stcg": {
        "amount": 55320.15,
        "coins": 2.332
      },
      "ltcg": {
        "amount": 8239.29,
        "coins": 3.245
      }
    },
    {
      "id": 6,
      "coin": "USDT",
      "coinName": "Tether",
      "logo": "/mock/images/tether.svg",
      "totalHolding": 3096.54,
      "averageBuyPrice": 1.15,
      "currentPrice": 1.01,
      "stcg": {
        "amount": -1200,
        "coins": 2011.23
      },
      "ltcg": {
        "amount": 2400,
        "coins": 802.47
      }
    }
  ]
}
